MANIFEST.in
README.md
requirements.txt
requirements_build.txt
requirements_dev.txt
setup.py
version.txt
apimas_django/__init__.py
apimas_django/collect_construction.py
apimas_django/db.py
apimas_django/execution.py
apimas_django/filtering.py
apimas_django/handlers.py
apimas_django/loaddata.py
apimas_django/ordering.py
apimas_django/pagination.py
apimas_django/permissions.py
apimas_django/predicates.py
apimas_django/processors.py
apimas_django/provider.py
apimas_django/search.py
apimas_django/utils.py
apimas_django/wrapper.py
apimas_django.egg-info/PKG-INFO
apimas_django.egg-info/SOURCES.txt
apimas_django.egg-info/dependency_links.txt
apimas_django.egg-info/requires.txt
apimas_django.egg-info/top_level.txt
apimas_django/test/__init__.py