Metadata-Version: 1.0
Name: apimas-django
Version: 0.4a4
Summary: APIMAS support for django applications
Home-page: UNKNOWN
Author: GRNET S.A.
Author-email: team@dev.grnet.gr
License: Affero GPL v3
Platform: UNKNOWN
